{
	"forge_marker": 1,
	"defaults": {
		"textures": {
			"all": "tfc2:blocks/rocks/Granite Raw"
		},
		"uvlock": true,
		"model": "tfc2:LooseRocks/rock0"
	},
	"variants": {
		"stone" : {
			"granite": {"textures": {"all": "tfc2:blocks/rocks/Granite Raw"}},
			"diorite": {"textures": {"all": "tfc2:blocks/rocks/Diorite Raw"}},
			"gabbro": {"textures": {"all": "tfc2:blocks/rocks/Gabbro Raw"}},
			"shale": {"textures": {"all": "tfc2:blocks/rocks/Shale Raw"}},
			"claystone": {"textures": {"all": "tfc2:blocks/rocks/Claystone Raw"}},
			"limestone": {"textures": {"all": "tfc2:blocks/rocks/Limestone Raw"}},
			"dolomite": {"textures": {"all": "tfc2:blocks/rocks/Dolomite Raw"}},
			"chert": {"textures": {"all": "tfc2:blocks/rocks/Chert Raw"}},
			"rhyolite": {"textures": {"all": "tfc2:blocks/rocks/Rhyolite Raw"}},
			"basalt": {"textures": {"all": "tfc2:blocks/rocks/Basalt Raw"}},
			"andesite": {"textures": {"all": "tfc2:blocks/rocks/Andesite Raw"}},
			"dacite": {"textures": {"all": "tfc2:blocks/rocks/Dacite Raw"}},
			"blueschist": {"textures": {"all": "tfc2:blocks/rocks/Blueschist Raw"}},
			"schist": {"textures": {"all": "tfc2:blocks/rocks/Schist Raw"}},
			"gneiss": {"textures": {"all": "tfc2:blocks/rocks/Gneiss Raw"}},
			"marble": {"textures": {"all": "tfc2:blocks/rocks/Marble Raw"}}
		},
		"stone=granite" : [{"y":0},{"y":90},{"y":180},{"y":270}, {"model": "tfc2:LooseRocks/rock1","y":0},{"model": "tfc2:LooseRocks/rock1","y":90},{"model": "tfc2:LooseRocks/rock1","y":180},{"model": "tfc2:LooseRocks/rock1","y":270}],
		"stone=diorite": [{"y":0},{"y":90},{"y":180},{"y":270}, {"model": "tfc2:LooseRocks/rock1","y":0},{"model": "tfc2:LooseRocks/rock1","y":90},{"model": "tfc2:LooseRocks/rock1","y":180},{"model": "tfc2:LooseRocks/rock1","y":270}],
		"stone=gabbro": [{"y":0},{"y":90},{"y":180},{"y":270}, {"model": "tfc2:LooseRocks/rock1","y":0},{"model": "tfc2:LooseRocks/rock1","y":90},{"model": "tfc2:LooseRocks/rock1","y":180},{"model": "tfc2:LooseRocks/rock1","y":270}],
		"stone=shale": [{"y":0},{"y":90},{"y":180},{"y":270}, {"model": "tfc2:LooseRocks/rock1","y":0},{"model": "tfc2:LooseRocks/rock1","y":90},{"model": "tfc2:LooseRocks/rock1","y":180},{"model": "tfc2:LooseRocks/rock1","y":270}],
		"stone=claystone": [{"y":0},{"y":90},{"y":180},{"y":270}, {"model": "tfc2:LooseRocks/rock1","y":0},{"model": "tfc2:LooseRocks/rock1","y":90},{"model": "tfc2:LooseRocks/rock1","y":180},{"model": "tfc2:LooseRocks/rock1","y":270}],
		"stone=limestone": [{"y":0},{"y":90},{"y":180},{"y":270}, {"model": "tfc2:LooseRocks/rock1","y":0},{"model": "tfc2:LooseRocks/rock1","y":90},{"model": "tfc2:LooseRocks/rock1","y":180},{"model": "tfc2:LooseRocks/rock1","y":270}],
		"stone=dolomite": [{"y":0},{"y":90},{"y":180},{"y":270}, {"model": "tfc2:LooseRocks/rock1","y":0},{"model": "tfc2:LooseRocks/rock1","y":90},{"model": "tfc2:LooseRocks/rock1","y":180},{"model": "tfc2:LooseRocks/rock1","y":270}],
		"stone=chert": [{"y":0},{"y":90},{"y":180},{"y":270}, {"model": "tfc2:LooseRocks/rock1","y":0},{"model": "tfc2:LooseRocks/rock1","y":90},{"model": "tfc2:LooseRocks/rock1","y":180},{"model": "tfc2:LooseRocks/rock1","y":270}],
		"stone=rhyolite": [{"y":0},{"y":90},{"y":180},{"y":270}, {"model": "tfc2:LooseRocks/rock1","y":0},{"model": "tfc2:LooseRocks/rock1","y":90},{"model": "tfc2:LooseRocks/rock1","y":180},{"model": "tfc2:LooseRocks/rock1","y":270}],
		"stone=basalt": [{"y":0},{"y":90},{"y":180},{"y":270}, {"model": "tfc2:LooseRocks/rock1","y":0},{"model": "tfc2:LooseRocks/rock1","y":90},{"model": "tfc2:LooseRocks/rock1","y":180},{"model": "tfc2:LooseRocks/rock1","y":270}],
		"stone=andesite": [{"y":0},{"y":90},{"y":180},{"y":270}, {"model": "tfc2:LooseRocks/rock1","y":0},{"model": "tfc2:LooseRocks/rock1","y":90},{"model": "tfc2:LooseRocks/rock1","y":180},{"model": "tfc2:LooseRocks/rock1","y":270}],
		"stone=dacite": [{"y":0},{"y":90},{"y":180},{"y":270}, {"model": "tfc2:LooseRocks/rock1","y":0},{"model": "tfc2:LooseRocks/rock1","y":90},{"model": "tfc2:LooseRocks/rock1","y":180},{"model": "tfc2:LooseRocks/rock1","y":270}],
		"stone=blueschist": [{"y":0},{"y":90},{"y":180},{"y":270}, {"model": "tfc2:LooseRocks/rock1","y":0},{"model": "tfc2:LooseRocks/rock1","y":90},{"model": "tfc2:LooseRocks/rock1","y":180},{"model": "tfc2:LooseRocks/rock1","y":270}],
		"stone=schist": [{"y":0},{"y":90},{"y":180},{"y":270}, {"model": "tfc2:LooseRocks/rock1","y":0},{"model": "tfc2:LooseRocks/rock1","y":90},{"model": "tfc2:LooseRocks/rock1","y":180},{"model": "tfc2:LooseRocks/rock1","y":270}],
		"stone=gneiss": [{"y":0},{"y":90},{"y":180},{"y":270}, {"model": "tfc2:LooseRocks/rock1","y":0},{"model": "tfc2:LooseRocks/rock1","y":90},{"model": "tfc2:LooseRocks/rock1","y":180},{"model": "tfc2:LooseRocks/rock1","y":270}],
		"stone=marble": [{"y":0},{"y":90},{"y":180},{"y":270}, {"model": "tfc2:LooseRocks/rock1","y":0},{"model": "tfc2:LooseRocks/rock1","y":90},{"model": "tfc2:LooseRocks/rock1","y":180},{"model": "tfc2:LooseRocks/rock1","y":270}]
	}
}
